{
  "generatedAt": "2026-05-30T00:12:21.802Z",
  "health": "ok",
  "errors": [],
  "summary": "Captured 173 updates across news, markets, FX, crypto, commodities, and Singapore policy sources.",
  "news": {
    "world": [
      {
        "title": "Meta plans 'Wearables for Work' and AI pendant, The Information reports",
        "url": "https://www.channelnewsasia.com/business/meta-plans-wearables-work-and-ai-pendant-information-reports-6150896",
        "source": "CNA Business",
        "category": "World finance",
        "date": "Sat, 30 May 2026 07:59:14 +0800",
        "summary": null
      },
      {
        "title": "Social media companies pay $27 million to settle Kentucky school district's lawsuit over social media harms, records show",
        "url": "https://www.channelnewsasia.com/business/social-media-companies-pay-27-million-settle-kentucky-school-districts-lawsuit-over-social-media-harms-records-show-6150886",
        "source": "CNA Business",
        "category": "World finance",
        "date": "Sat, 30 May 2026 07:48:25 +0800",
        "summary": null
      },
      {
        "title": "Commentary: What if remote working, not AI, is to blame for weak junior hiring?",
        "url": "https://www.channelnewsasia.com/commentary/remote-work-impact-younger-workers-ai-career-progression-6149286",
        "source": "CNA World",
        "category": "World news",
        "date": "Sat, 30 May 2026 06:00:00 +0800",
        "summary": "New evidence suggests the rise of working from home has made entry-level hires a less attractive proposition, according to this Financial Times writer."
      },
      {
        "title": "Oil falls, stocks mixed on US-Iran truce prospects",
        "url": "https://www.channelnewsasia.com/world/oil-prices-stocks-market-us-iran-deal-6150796",
        "source": "CNA World",
        "category": "World news",
        "date": "Sat, 30 May 2026 05:36:19 +0800",
        "summary": "Analysts said oil traders were taking an \"optimistic view\" that disruption in the region could soon ease."
      },
      {
        "title": "Universal rejects billionaire Bill Ackman's takeover bid",
        "url": "https://www.bbc.com/news/articles/cn8pnd9yj4eo?at_medium=RSS&at_campaign=rss",
        "source": "BBC Business",
        "category": "World finance",
        "date": "Fri, 29 May 2026 19:29:12 GMT",
        "summary": "The music giant said Pershing Square's offer fundamentally undervalued the business."
      },
      {
        "title": "SpaceX wins $4.16 billion US Space Force contract for threat-detection satellites",
        "url": "https://www.channelnewsasia.com/business/spacex-wins-416-billion-us-space-force-contract-threat-detection-satellites-6150646",
        "source": "CNA Business",
        "category": "World finance",
        "date": "Sat, 30 May 2026 03:25:16 +0800",
        "summary": null
      },
      {
        "title": "UK banks still lack access to Mythos AI model, BoE's Bailey says",
        "url": "https://www.channelnewsasia.com/business/uk-banks-still-lack-access-mythos-ai-model-boes-bailey-says-6150626",
        "source": "CNA Business",
        "category": "World finance",
        "date": "Sat, 30 May 2026 02:50:37 +0800",
        "summary": null
      }
    ],
    "singapore": [
      {
        "title": "Singapore workers likely to feel AI disruption sooner than most: ESR committee on human capital",
        "url": "https://www.channelnewsasia.com/singapore/economic-strategy-review-esr-committee-human-capital-interview-david-neo-marcus-lam-6149426",
        "source": "CNA Singapore",
        "category": "Singapore news",
        "date": "Fri, 29 May 2026 16:40:00 +0800",
        "summary": "The nation must continue accelerating AI adoption, as slowing down would ultimately hurt Singapore's workers, said the committee."
      },
      {
        "title": "Annette Lee says she'll refund moviegoers if her new film Dream Stall 'wasted their time'",
        "url": "https://www.channelnewsasia.com/entertainment/annette-lee-dream-stall-refund-6148961",
        "source": "CNA Singapore",
        "category": "Singapore news",
        "date": "Fri, 29 May 2026 13:18:00 +0800",
        "summary": "The creator and director-writer insisted her refund promise was \"not a joke\" and wanted honest feedback from moviegoers."
      },
      {
        "title": "Singer Frances Tan swapped law for music, now represents Singapore in Commonwealth Song Contest finals",
        "url": "https://www.channelnewsasia.com/entertainment/frances-tan-commonwealth-song-contest-6148836",
        "source": "CNA Singapore",
        "category": "Singapore news",
        "date": "Fri, 29 May 2026 11:59:00 +0800",
        "summary": "Public voting for the Commonwealth Song Contest 2026 ends on May 31. On the same day, Tan will host a free concert to launch her debut album, I Am Frances."
      },
      {
        "title": "123,000 AIS Employers to Submit Employees' Employment Income Data by 1 Mar 2026, Enabling IRAS to Pre-fill Over 2 Million Tax Returns",
        "url": "https://www.iras.gov.sg/news-events/newsroom/123-000-ais-employers-to-submit-employees--employment-income-data-by-1-mar-2026--enabling-iras-to-pre-fill-over-2-million-tax-returns",
        "source": "IRAS",
        "category": "Tax policy",
        "date": null
      },
      {
        "title": "Businesswoman Faces Charges for Evading Over $370,000 in Income Tax and Giving False Documents to IRAS",
        "url": "https://www.iras.gov.sg/news-events/newsroom/businesswoman-faces-charges-for-evading-over--370-000-in-income-tax-and-giving-false-documents-to-iras",
        "source": "IRAS",
        "category": "Tax policy",
        "date": null
      },
      {
        "title": "CPF Board to introduce new investment scheme in 2028 offering simplified, low-cost, and diversified commercial investment products",
        "url": "https://www.cpf.gov.sg/member/infohub/news/news-releases/cpfb-to-introduce-new-investment-scheme-in-2028",
        "source": "CPF",
        "category": "Retirement policy",
        "date": null
      },
      {
        "title": "CPF Board marks 70th anniversary with launch of one-stop financial guidance platform 'PLAN with CPF' & commemorative book",
        "url": "https://www.cpf.gov.sg/member/infohub/news/news-releases/cpf-board-marks-70th-anniversary-with-launch-of-plan-with-cpf-and-commemorative-book",
        "source": "CPF",
        "category": "Retirement policy",
        "date": null
      },
      {
        "title": "440,000 CPF Members qualify for Matched Retirement Savings Scheme in 2021",
        "url": "https://www.cpf.gov.sg/member/infohub/news/news-releases/440000-cpf-members-qualify-for-matched-retirement-savings-scheme-in-2021",
        "source": "CPF",
        "category": "Retirement policy",
        "date": null
      }
    ]
  },
  "markets": {
    "us": {
      "gainers": [
        {
          "symbol": "DELL",
          "name": "Dell Technologies Inc.",
          "price": 420.91,
          "changePct": 32.7582,
          "url": "https://www.nasdaq.com/market-activity/stocks/dell"
        },
        {
          "symbol": "OKTA",
          "name": "Okta, Inc.",
          "price": 123.27,
          "changePct": 30.1415,
          "url": "https://www.nasdaq.com/market-activity/stocks/okta"
        },
        {
          "symbol": "NTAP",
          "name": "NetApp, Inc.",
          "price": 174.29,
          "changePct": 22.3947,
          "url": "https://www.nasdaq.com/market-activity/stocks/ntap"
        },
        {
          "symbol": "TBBB",
          "name": "BBB Foods Inc.",
          "price": 37.82,
          "changePct": 15.5515,
          "url": "https://www.nasdaq.com/market-activity/stocks/tbbb"
        },
        {
          "symbol": "TEAM",
          "name": "Atlassian Corporation",
          "price": 107.61,
          "changePct": 15.35,
          "url": "https://www.nasdaq.com/market-activity/stocks/team"
        },
        {
          "symbol": "FPS",
          "name": "Forgent Power Solutions, Inc.",
          "price": 54.66,
          "changePct": 14.9285,
          "url": "https://www.nasdaq.com/market-activity/stocks/fps"
        },
        {
          "symbol": "NOW",
          "name": "ServiceNow, Inc.",
          "price": 124.37,
          "changePct": 14.3843,
          "url": "https://www.nasdaq.com/market-activity/stocks/now"
        },
        {
          "symbol": "NXT",
          "name": "Nextpower Inc.",
          "price": 156.4,
          "changePct": 14.0191,
          "url": "https://www.nasdaq.com/market-activity/stocks/nxt"
        },
        {
          "symbol": "SAIL",
          "name": "SailPoint, Inc.",
          "price": 18.83,
          "changePct": 13.7764,
          "url": "https://www.nasdaq.com/market-activity/stocks/sail"
        },
        {
          "symbol": "ZETA",
          "name": "Zeta Global Holdings Corp.",
          "price": 22.89,
          "changePct": 13.4291,
          "url": "https://www.nasdaq.com/market-activity/stocks/zeta"
        },
        {
          "symbol": "IBM",
          "name": "International Business Machines",
          "price": 297.8,
          "changePct": 12.7091,
          "url": "https://www.nasdaq.com/market-activity/stocks/ibm"
        },
        {
          "symbol": "HPE",
          "name": "Hewlett Packard Enterprise Comp",
          "price": 43.04,
          "changePct": 12.6407,
          "url": "https://www.nasdaq.com/market-activity/stocks/hpe"
        },
        {
          "symbol": "WDAY",
          "name": "Workday, Inc.",
          "price": 146.19,
          "changePct": 12.4452,
          "url": "https://www.nasdaq.com/market-activity/stocks/wday"
        },
        {
          "symbol": "ESTC",
          "name": "Elastic N.V.",
          "price": 64.7,
          "changePct": 12.3069,
          "url": "https://www.nasdaq.com/market-activity/stocks/estc"
        },
        {
          "symbol": "RBRK",
          "name": "Rubrik, Inc.",
          "price": 78.63,
          "changePct": 11.8174,
          "url": "https://www.nasdaq.com/market-activity/stocks/rbrk"
        }
      ],
      "losers": [
        {
          "symbol": "AMBA",
          "name": "Ambarella, Inc.",
          "price": 72.18,
          "changePct": -21.4068,
          "url": "https://www.nasdaq.com/market-activity/stocks/amba"
        },
        {
          "symbol": "GAP",
          "name": "Gap, Inc. (The)",
          "price": 21.15,
          "changePct": -15.4,
          "url": "https://www.nasdaq.com/market-activity/stocks/gap"
        },
        {
          "symbol": "ASTS",
          "name": "AST SpaceMobile, Inc.",
          "price": 113.41,
          "changePct": -14.787,
          "url": "https://www.nasdaq.com/market-activity/stocks/asts"
        },
        {
          "symbol": "KRMN",
          "name": "Karman Holdings Inc.",
          "price": 57.5,
          "changePct": -12.6936,
          "url": "https://www.nasdaq.com/market-activity/stocks/krmn"
        },
        {
          "symbol": "AEO",
          "name": "American Eagle Outfitters, Inc.",
          "price": 15.8,
          "changePct": -11.8304,
          "url": "https://www.nasdaq.com/market-activity/stocks/aeo"
        },
        {
          "symbol": "FLNC",
          "name": "Fluence Energy, Inc.",
          "price": 18.88,
          "changePct": -11.6105,
          "url": "https://www.nasdaq.com/market-activity/stocks/flnc"
        },
        {
          "symbol": "AXTI",
          "name": "AXT Inc",
          "price": 103.16,
          "changePct": -10.8384,
          "url": "https://www.nasdaq.com/market-activity/stocks/axti"
        },
        {
          "symbol": "CECO",
          "name": "CECO Environmental Corp.",
          "price": 74.75,
          "changePct": -10.2749,
          "url": "https://www.nasdaq.com/market-activity/stocks/ceco"
        },
        {
          "symbol": "HCC",
          "name": "Warrior Met Coal, Inc.",
          "price": 94.54,
          "changePct": -9.60031,
          "url": "https://www.nasdaq.com/market-activity/stocks/hcc"
        },
        {
          "symbol": "BKE",
          "name": "Buckle, Inc. (The)",
          "price": 45.87,
          "changePct": -9.13233,
          "url": "https://www.nasdaq.com/market-activity/stocks/bke"
        },
        {
          "symbol": "WOLF",
          "name": "Wolfspeed, Inc.",
          "price": 59.28,
          "changePct": -8.87011,
          "url": "https://www.nasdaq.com/market-activity/stocks/wolf"
        },
        {
          "symbol": "EQPT",
          "name": "EquipmentShare.com Inc",
          "price": 20.84,
          "changePct": -8.8364,
          "url": "https://www.nasdaq.com/market-activity/stocks/eqpt"
        },
        {
          "symbol": "INFQ",
          "name": "Infleqtion, Inc.",
          "price": 16.22,
          "changePct": -8.72257,
          "url": "https://www.nasdaq.com/market-activity/stocks/infq"
        },
        {
          "symbol": "THR",
          "name": "Thermon Group Holdings, Inc.",
          "price": 61.14,
          "changePct": -8.48675,
          "url": "https://www.nasdaq.com/market-activity/stocks/thr"
        },
        {
          "symbol": "SMTC",
          "name": "Semtech Corporation",
          "price": 152.54,
          "changePct": -8.29075,
          "url": "https://www.nasdaq.com/market-activity/stocks/smtc"
        }
      ]
    },
    "sgx": {
      "gainers": [
        {
          "symbol": "F34",
          "name": "Wilmar · SGX equity",
          "price": 3.59,
          "changePct": 5.89970173766347,
          "url": "https://www.sgx.com/securities/equities/F34"
        },
        {
          "symbol": "J36",
          "name": "Jardine Matheson · SGX equity",
          "price": 66.38,
          "changePct": 3.395643544212812,
          "url": "https://www.sgx.com/securities/equities/J36"
        },
        {
          "symbol": "C09",
          "name": "City Developments · SGX equity",
          "price": 8.58,
          "changePct": 2.508961975056119,
          "url": "https://www.sgx.com/securities/equities/C09"
        },
        {
          "symbol": "S68",
          "name": "Singapore Exchange · SGX equity",
          "price": 21.88,
          "changePct": 2.0046583765324764,
          "url": "https://www.sgx.com/securities/equities/S68"
        },
        {
          "symbol": "M44U",
          "name": "Mapletree Logistics Trust · SGX equity",
          "price": 1.2,
          "changePct": 1.6949197746701832,
          "url": "https://www.sgx.com/securities/equities/M44U"
        },
        {
          "symbol": "D05",
          "name": "DBS Group · SGX equity",
          "price": 62.84,
          "changePct": 1.469400436525057,
          "url": "https://www.sgx.com/securities/equities/D05"
        },
        {
          "symbol": "S58",
          "name": "SATS · SGX equity",
          "price": 3.85,
          "changePct": 1.3157907450298376,
          "url": "https://www.sgx.com/securities/equities/S58"
        },
        {
          "symbol": "C6L",
          "name": "Singapore Airlines · SGX equity",
          "price": 6.78,
          "changePct": 1.0432185015658915,
          "url": "https://www.sgx.com/securities/equities/C6L"
        },
        {
          "symbol": "O39",
          "name": "OCBC Bank · SGX equity",
          "price": 23.4,
          "changePct": 1.0362700957215538,
          "url": "https://www.sgx.com/securities/equities/O39"
        },
        {
          "symbol": "G13",
          "name": "Genting Singapore · SGX equity",
          "price": 0.6,
          "changePct": 0.8403312856050045,
          "url": "https://www.sgx.com/securities/equities/G13"
        },
        {
          "symbol": "N2IU",
          "name": "Mapletree Pan Asia Commercial Trust · SGX equity",
          "price": 1.28,
          "changePct": 0.7874030884780768,
          "url": "https://www.sgx.com/securities/equities/N2IU"
        },
        {
          "symbol": "T82U",
          "name": "Suntec REIT · SGX equity",
          "price": 1.47,
          "changePct": 0.6849288761471017,
          "url": "https://www.sgx.com/securities/equities/T82U"
        },
        {
          "symbol": "BN4",
          "name": "Keppel · SGX equity",
          "price": 10.76,
          "changePct": 0.3731318281233369,
          "url": "https://www.sgx.com/securities/equities/BN4"
        },
        {
          "symbol": "Y92",
          "name": "Thai Beverage · SGX equity",
          "price": 0.45,
          "changePct": 0.000002649095395994919,
          "url": "https://www.sgx.com/securities/equities/Y92"
        },
        {
          "symbol": "BS6",
          "name": "Yangzijiang Shipbuilding · SGX equity",
          "price": 3.64,
          "changePct": -0.000002881982737830283,
          "url": "https://www.sgx.com/securities/equities/BS6"
        }
      ],
      "losers": [
        {
          "symbol": "Z74",
          "name": "Singtel · SGX equity",
          "price": 4.34,
          "changePct": -0.4587186445401141,
          "url": "https://www.sgx.com/securities/equities/Z74"
        },
        {
          "symbol": "C38U",
          "name": "CapitaLand Integrated Commercial Trust · SGX equity",
          "price": 2.27,
          "changePct": -0.4385952418970875,
          "url": "https://www.sgx.com/securities/equities/C38U"
        },
        {
          "symbol": "A17U",
          "name": "CapitaLand Ascendas REIT · SGX equity",
          "price": 2.5,
          "changePct": -0.3984059960658085,
          "url": "https://www.sgx.com/securities/equities/A17U"
        },
        {
          "symbol": "U11",
          "name": "UOB · SGX equity",
          "price": 37.6,
          "changePct": -0.2387864950602718,
          "url": "https://www.sgx.com/securities/equities/U11"
        },
        {
          "symbol": "BS6",
          "name": "Yangzijiang Shipbuilding · SGX equity",
          "price": 3.64,
          "changePct": -0.000002881982737830283,
          "url": "https://www.sgx.com/securities/equities/BS6"
        },
        {
          "symbol": "Y92",
          "name": "Thai Beverage · SGX equity",
          "price": 0.45,
          "changePct": 0.000002649095395994919,
          "url": "https://www.sgx.com/securities/equities/Y92"
        },
        {
          "symbol": "BN4",
          "name": "Keppel · SGX equity",
          "price": 10.76,
          "changePct": 0.3731318281233369,
          "url": "https://www.sgx.com/securities/equities/BN4"
        },
        {
          "symbol": "T82U",
          "name": "Suntec REIT · SGX equity",
          "price": 1.47,
          "changePct": 0.6849288761471017,
          "url": "https://www.sgx.com/securities/equities/T82U"
        },
        {
          "symbol": "N2IU",
          "name": "Mapletree Pan Asia Commercial Trust · SGX equity",
          "price": 1.28,
          "changePct": 0.7874030884780768,
          "url": "https://www.sgx.com/securities/equities/N2IU"
        },
        {
          "symbol": "G13",
          "name": "Genting Singapore · SGX equity",
          "price": 0.6,
          "changePct": 0.8403312856050045,
          "url": "https://www.sgx.com/securities/equities/G13"
        },
        {
          "symbol": "O39",
          "name": "OCBC Bank · SGX equity",
          "price": 23.4,
          "changePct": 1.0362700957215538,
          "url": "https://www.sgx.com/securities/equities/O39"
        },
        {
          "symbol": "C6L",
          "name": "Singapore Airlines · SGX equity",
          "price": 6.78,
          "changePct": 1.0432185015658915,
          "url": "https://www.sgx.com/securities/equities/C6L"
        },
        {
          "symbol": "S58",
          "name": "SATS · SGX equity",
          "price": 3.85,
          "changePct": 1.3157907450298376,
          "url": "https://www.sgx.com/securities/equities/S58"
        },
        {
          "symbol": "D05",
          "name": "DBS Group · SGX equity",
          "price": 62.84,
          "changePct": 1.469400436525057,
          "url": "https://www.sgx.com/securities/equities/D05"
        },
        {
          "symbol": "M44U",
          "name": "Mapletree Logistics Trust · SGX equity",
          "price": 1.2,
          "changePct": 1.6949197746701832,
          "url": "https://www.sgx.com/securities/equities/M44U"
        }
      ]
    },
    "etfs": {
      "gainers": [
        {
          "symbol": "GLD",
          "name": "SPDR Gold Shares · US ETF",
          "price": 417.12,
          "changePct": 1.0538583477744181,
          "url": "https://www.nasdaq.com/market-activity/etf/gld"
        },
        {
          "symbol": "DIA",
          "name": "SPDR Dow Jones Industrial Average ETF · US ETF",
          "price": 510.78,
          "changePct": 0.7356300753041743,
          "url": "https://www.nasdaq.com/market-activity/etf/dia"
        },
        {
          "symbol": "QQQ",
          "name": "Invesco QQQ Trust · US ETF",
          "price": 738.31,
          "changePct": 0.3684100739540934,
          "url": "https://www.nasdaq.com/market-activity/etf/qqq"
        },
        {
          "symbol": "G3B",
          "name": "Nikko AM Singapore STI ETF · SG ETF",
          "price": 5.241,
          "changePct": 0.3254215727922347,
          "url": "https://www.sgx.com/securities/etf/G3B"
        },
        {
          "symbol": "SPY",
          "name": "SPDR S&P 500 ETF · US ETF",
          "price": 756.48,
          "changePct": 0.24914185991096843,
          "url": "https://www.nasdaq.com/market-activity/etf/spy"
        },
        {
          "symbol": "CLR",
          "name": "Lion-OCBC Securities Singapore Low Carbon ETF · SG ETF",
          "price": 0.826,
          "changePct": 0.24271833058384681,
          "url": "https://www.sgx.com/securities/etf/CLR"
        },
        {
          "symbol": "VTI",
          "name": "Vanguard Total Stock Market ETF · US ETF",
          "price": 372.54,
          "changePct": 0.2367745598718458,
          "url": "https://www.nasdaq.com/market-activity/etf/vti"
        },
        {
          "symbol": "A35",
          "name": "ABF Singapore Bond Index Fund · SG ETF",
          "price": 1.15,
          "changePct": 0.1742158614397539,
          "url": "https://www.sgx.com/securities/etf/A35"
        },
        {
          "symbol": "VEA",
          "name": "Vanguard FTSE Developed Markets ETF · US ETF",
          "price": 71.77,
          "changePct": 0.15349753316965317,
          "url": "https://www.nasdaq.com/market-activity/etf/vea"
        },
        {
          "symbol": "HYG",
          "name": "iShares iBoxx High Yield Corporate Bond ETF · US ETF",
          "price": 80.31,
          "changePct": 0.09970913588338408,
          "url": "https://www.nasdaq.com/market-activity/etf/hyg"
        },
        {
          "symbol": "MBH",
          "name": "Nikko AM SGD Investment Grade Corporate Bond ETF · SG ETF",
          "price": 1.013,
          "changePct": 0.09881771944845637,
          "url": "https://www.sgx.com/securities/etf/MBH"
        },
        {
          "symbol": "TLT",
          "name": "iShares 20+ Year Treasury Bond ETF · US ETF",
          "price": 85.76,
          "changePct": 0.023328827535376007,
          "url": "https://www.nasdaq.com/market-activity/etf/tlt"
        },
        {
          "symbol": "VWO",
          "name": "Vanguard FTSE Emerging Markets ETF · US ETF",
          "price": 59.88,
          "changePct": -0.033391528162586656,
          "url": "https://www.nasdaq.com/market-activity/etf/vwo"
        },
        {
          "symbol": "SLV",
          "name": "iShares Silver Trust · US ETF",
          "price": 68.33,
          "changePct": -0.04388620550571104,
          "url": "https://www.nasdaq.com/market-activity/etf/slv"
        },
        {
          "symbol": "ES3",
          "name": "SPDR Straits Times Index ETF · SG ETF",
          "price": 5.12,
          "changePct": -0.09756097560975402,
          "url": "https://www.sgx.com/securities/etf/ES3"
        }
      ],
      "losers": [
        {
          "symbol": "USO",
          "name": "United States Oil Fund · US ETF",
          "price": 129.09,
          "changePct": -1.2922455995346032,
          "url": "https://www.nasdaq.com/market-activity/etf/uso"
        },
        {
          "symbol": "OVQ",
          "name": "Lion-OCBC Securities Hang Seng TECH ETF · SG ETF",
          "price": 1.501,
          "changePct": -1.1849935992697151,
          "url": "https://www.sgx.com/securities/etf/OVQ"
        },
        {
          "symbol": "HST",
          "name": "Lion-OCBC Securities Hang Seng TECH ETF · SG ETF",
          "price": 0.779,
          "changePct": -1.1421304243442283,
          "url": "https://www.sgx.com/securities/etf/HST"
        },
        {
          "symbol": "IWM",
          "name": "iShares Russell 2000 ETF · US ETF",
          "price": 290.43,
          "changePct": -0.5478884998065131,
          "url": "https://www.nasdaq.com/market-activity/etf/iwm"
        },
        {
          "symbol": "CFA",
          "name": "NikkoAM-StraitsTrading Asia ex Japan REIT ETF · SG ETF",
          "price": 0.796,
          "changePct": -0.25062382461952226,
          "url": "https://www.sgx.com/securities/etf/CFA"
        },
        {
          "symbol": "ES3",
          "name": "SPDR Straits Times Index ETF · SG ETF",
          "price": 5.12,
          "changePct": -0.09756097560975402,
          "url": "https://www.sgx.com/securities/etf/ES3"
        },
        {
          "symbol": "SLV",
          "name": "iShares Silver Trust · US ETF",
          "price": 68.33,
          "changePct": -0.04388620550571104,
          "url": "https://www.nasdaq.com/market-activity/etf/slv"
        },
        {
          "symbol": "VWO",
          "name": "Vanguard FTSE Emerging Markets ETF · US ETF",
          "price": 59.88,
          "changePct": -0.033391528162586656,
          "url": "https://www.nasdaq.com/market-activity/etf/vwo"
        },
        {
          "symbol": "TLT",
          "name": "iShares 20+ Year Treasury Bond ETF · US ETF",
          "price": 85.76,
          "changePct": 0.023328827535376007,
          "url": "https://www.nasdaq.com/market-activity/etf/tlt"
        },
        {
          "symbol": "MBH",
          "name": "Nikko AM SGD Investment Grade Corporate Bond ETF · SG ETF",
          "price": 1.013,
          "changePct": 0.09881771944845637,
          "url": "https://www.sgx.com/securities/etf/MBH"
        },
        {
          "symbol": "HYG",
          "name": "iShares iBoxx High Yield Corporate Bond ETF · US ETF",
          "price": 80.31,
          "changePct": 0.09970913588338408,
          "url": "https://www.nasdaq.com/market-activity/etf/hyg"
        },
        {
          "symbol": "VEA",
          "name": "Vanguard FTSE Developed Markets ETF · US ETF",
          "price": 71.77,
          "changePct": 0.15349753316965317,
          "url": "https://www.nasdaq.com/market-activity/etf/vea"
        },
        {
          "symbol": "A35",
          "name": "ABF Singapore Bond Index Fund · SG ETF",
          "price": 1.15,
          "changePct": 0.1742158614397539,
          "url": "https://www.sgx.com/securities/etf/A35"
        },
        {
          "symbol": "VTI",
          "name": "Vanguard Total Stock Market ETF · US ETF",
          "price": 372.54,
          "changePct": 0.2367745598718458,
          "url": "https://www.nasdaq.com/market-activity/etf/vti"
        },
        {
          "symbol": "CLR",
          "name": "Lion-OCBC Securities Singapore Low Carbon ETF · SG ETF",
          "price": 0.826,
          "changePct": 0.24271833058384681,
          "url": "https://www.sgx.com/securities/etf/CLR"
        }
      ]
    },
    "crypto": {
      "gainers": [
        {
          "symbol": "XLM",
          "name": "Stellar",
          "price": 0.333204,
          "changePct": 27.26594,
          "url": "https://www.coingecko.com/en/coins/stellar"
        },
        {
          "symbol": "XMR",
          "name": "Monero",
          "price": 509.55,
          "changePct": 12.81849,
          "url": "https://www.coingecko.com/en/coins/monero"
        },
        {
          "symbol": "HBAR",
          "name": "Hedera",
          "price": 0.128621,
          "changePct": 9.31141,
          "url": "https://www.coingecko.com/en/coins/hedera-hashgraph"
        },
        {
          "symbol": "HYPE",
          "name": "Hyperliquid",
          "price": 82.18,
          "changePct": 4.78689,
          "url": "https://www.coingecko.com/en/coins/hyperliquid"
        },
        {
          "symbol": "MNT",
          "name": "Mantle",
          "price": 0.821791,
          "changePct": 2.05699,
          "url": "https://www.coingecko.com/en/coins/mantle"
        },
        {
          "symbol": "CRO",
          "name": "Cronos",
          "price": 0.086978,
          "changePct": 1.77575,
          "url": "https://www.coingecko.com/en/coins/crypto-com-chain"
        },
        {
          "symbol": "RAIN",
          "name": "Rain",
          "price": 0.01847271,
          "changePct": 1.43858,
          "url": "https://www.coingecko.com/en/coins/rain"
        },
        {
          "symbol": "FIGR_HELOC",
          "name": "Figure Heloc",
          "price": 1.32,
          "changePct": 1.34134,
          "url": "https://www.coingecko.com/en/coins/figure-heloc"
        },
        {
          "symbol": "SHIB",
          "name": "Shiba Inu",
          "price": 0.00000693,
          "changePct": 1.13632,
          "url": "https://www.coingecko.com/en/coins/shiba-inu"
        },
        {
          "symbol": "PAXG",
          "name": "PAX Gold",
          "price": 5784.08,
          "changePct": 1.10371,
          "url": "https://www.coingecko.com/en/coins/pax-gold"
        },
        {
          "symbol": "XAUT",
          "name": "Tether Gold",
          "price": 5769.65,
          "changePct": 1.05668,
          "url": "https://www.coingecko.com/en/coins/tether-gold"
        },
        {
          "symbol": "BNB",
          "name": "BNB",
          "price": 821.39,
          "changePct": 0.86131,
          "url": "https://www.coingecko.com/en/coins/binancecoin"
        },
        {
          "symbol": "XRP",
          "name": "XRP",
          "price": 1.7,
          "changePct": 0.82247,
          "url": "https://www.coingecko.com/en/coins/ripple"
        },
        {
          "symbol": "BCH",
          "name": "Bitcoin Cash",
          "price": 386.53,
          "changePct": 0.6675,
          "url": "https://www.coingecko.com/en/coins/bitcoin-cash"
        },
        {
          "symbol": "LTC",
          "name": "Litecoin",
          "price": 66.27,
          "changePct": 0.56558,
          "url": "https://www.coingecko.com/en/coins/litecoin"
        }
      ],
      "losers": [
        {
          "symbol": "ONDO",
          "name": "Ondo",
          "price": 0.452331,
          "changePct": -4.1616,
          "url": "https://www.coingecko.com/en/coins/ondo-finance"
        },
        {
          "symbol": "TAO",
          "name": "Bittensor",
          "price": 321.2,
          "changePct": -3.4662,
          "url": "https://www.coingecko.com/en/coins/bittensor"
        },
        {
          "symbol": "ICP",
          "name": "Internet Computer",
          "price": 3.38,
          "changePct": -2.92837,
          "url": "https://www.coingecko.com/en/coins/internet-computer"
        },
        {
          "symbol": "SUI",
          "name": "Sui",
          "price": 1.15,
          "changePct": -2.82156,
          "url": "https://www.coingecko.com/en/coins/sui"
        },
        {
          "symbol": "ZEC",
          "name": "Zcash",
          "price": 678.21,
          "changePct": -2.59667,
          "url": "https://www.coingecko.com/en/coins/zcash"
        },
        {
          "symbol": "HTX",
          "name": "HTX DAO",
          "price": 0.00000232,
          "changePct": -2.43766,
          "url": "https://www.coingecko.com/en/coins/htx-dao"
        },
        {
          "symbol": "TRX",
          "name": "TRON",
          "price": 0.439176,
          "changePct": -2.1913,
          "url": "https://www.coingecko.com/en/coins/tron"
        },
        {
          "symbol": "DOT",
          "name": "Polkadot",
          "price": 1.53,
          "changePct": -1.55281,
          "url": "https://www.coingecko.com/en/coins/polkadot"
        },
        {
          "symbol": "OKB",
          "name": "OKB",
          "price": 111.18,
          "changePct": -1.40691,
          "url": "https://www.coingecko.com/en/coins/okb"
        },
        {
          "symbol": "NEAR",
          "name": "NEAR Protocol",
          "price": 3.05,
          "changePct": -1.40539,
          "url": "https://www.coingecko.com/en/coins/near"
        },
        {
          "symbol": "UNI",
          "name": "Uniswap",
          "price": 3.86,
          "changePct": -1.20362,
          "url": "https://www.coingecko.com/en/coins/uniswap"
        },
        {
          "symbol": "AVAX",
          "name": "Avalanche",
          "price": 11.26,
          "changePct": -1.1758,
          "url": "https://www.coingecko.com/en/coins/avalanche-2"
        },
        {
          "symbol": "PI",
          "name": "Pi Network",
          "price": 0.182851,
          "changePct": -1.10545,
          "url": "https://www.coingecko.com/en/coins/pi-network"
        },
        {
          "symbol": "TON",
          "name": "Toncoin",
          "price": 2.24,
          "changePct": -0.86641,
          "url": "https://www.coingecko.com/en/coins/the-open-network"
        },
        {
          "symbol": "ADA",
          "name": "Cardano",
          "price": 0.297244,
          "changePct": -0.76996,
          "url": "https://www.coingecko.com/en/coins/cardano"
        }
      ]
    },
    "commodities": {
      "gainers": [
        {
          "symbol": "HE",
          "name": "Lean hog futures · Commodity",
          "price": 99.775,
          "changePct": 2.887343717387245,
          "url": "https://www.cmegroup.com/search.html?q=Lean%20hog%20futures"
        },
        {
          "symbol": "GC",
          "name": "Gold futures · Commodity",
          "price": 4569.9,
          "changePct": 1.5691373853092945,
          "url": "https://www.cmegroup.com/search.html?q=Gold%20futures"
        },
        {
          "symbol": "SB",
          "name": "Sugar futures · Commodity",
          "price": 14.07,
          "changePct": 1.005022912829379,
          "url": "https://www.cmegroup.com/search.html?q=Sugar%20futures"
        },
        {
          "symbol": "PL",
          "name": "Platinum futures · Commodity",
          "price": 1922.9,
          "changePct": 0.06765322806929082,
          "url": "https://www.cmegroup.com/search.html?q=Platinum%20futures"
        },
        {
          "symbol": "HG",
          "name": "Copper futures · Commodity",
          "price": 6.394,
          "changePct": -0.03126811250613366,
          "url": "https://www.cmegroup.com/search.html?q=Copper%20futures"
        },
        {
          "symbol": "SI",
          "name": "Silver futures · Commodity",
          "price": 75.585,
          "changePct": -0.07931343212229724,
          "url": "https://www.cmegroup.com/search.html?q=Silver%20futures"
        },
        {
          "symbol": "NG",
          "name": "Natural gas futures · Commodity",
          "price": 3.273,
          "changePct": -0.3652994069147443,
          "url": "https://www.cmegroup.com/search.html?q=Natural%20gas%20futures"
        },
        {
          "symbol": "PA",
          "name": "Palladium futures · Commodity",
          "price": 1368.5,
          "changePct": -0.6605673451806638,
          "url": "https://www.cmegroup.com/search.html?q=Palladium%20futures"
        },
        {
          "symbol": "ZS",
          "name": "Soybean futures · Commodity",
          "price": 1186.5,
          "changePct": -0.6697362913352868,
          "url": "https://www.cmegroup.com/search.html?q=Soybean%20futures"
        },
        {
          "symbol": "CT",
          "name": "Cotton futures · Commodity",
          "price": 76.25,
          "changePct": -0.6773435792684387,
          "url": "https://www.cmegroup.com/search.html?q=Cotton%20futures"
        },
        {
          "symbol": "CL",
          "name": "WTI crude futures · Commodity",
          "price": 87.76,
          "changePct": -1.282341401925674,
          "url": "https://www.cmegroup.com/search.html?q=WTI%20crude%20futures"
        },
        {
          "symbol": "ZC",
          "name": "Corn futures · Commodity",
          "price": 447,
          "changePct": -1.9199122325836533,
          "url": "https://www.cmegroup.com/search.html?q=Corn%20futures"
        },
        {
          "symbol": "BZ",
          "name": "Brent crude futures · Commodity",
          "price": 91.7,
          "changePct": -2.144914207779244,
          "url": "https://www.cmegroup.com/search.html?q=Brent%20crude%20futures"
        },
        {
          "symbol": "ZW",
          "name": "Wheat futures · Commodity",
          "price": 610.25,
          "changePct": -2.203525641025641,
          "url": "https://www.cmegroup.com/search.html?q=Wheat%20futures"
        },
        {
          "symbol": "HO",
          "name": "Heating oil futures · Commodity",
          "price": 3.5129,
          "changePct": -2.9237026186973574,
          "url": "https://www.cmegroup.com/search.html?q=Heating%20oil%20futures"
        }
      ],
      "losers": [
        {
          "symbol": "CC",
          "name": "Cocoa futures · Commodity",
          "price": 3901,
          "changePct": -4.830446450353745,
          "url": "https://www.cmegroup.com/search.html?q=Cocoa%20futures"
        },
        {
          "symbol": "RB",
          "name": "RBOB gasoline futures · Commodity",
          "price": 3.0469,
          "changePct": -4.341955827291594,
          "url": "https://www.cmegroup.com/search.html?q=RBOB%20gasoline%20futures"
        },
        {
          "symbol": "LE",
          "name": "Live cattle futures · Commodity",
          "price": 239.2,
          "changePct": -4.224224224224229,
          "url": "https://www.cmegroup.com/search.html?q=Live%20cattle%20futures"
        },
        {
          "symbol": "KC",
          "name": "Coffee futures · Commodity",
          "price": 265.9,
          "changePct": -3.0446672743846936,
          "url": "https://www.cmegroup.com/search.html?q=Coffee%20futures"
        },
        {
          "symbol": "HO",
          "name": "Heating oil futures · Commodity",
          "price": 3.5129,
          "changePct": -2.9237026186973574,
          "url": "https://www.cmegroup.com/search.html?q=Heating%20oil%20futures"
        },
        {
          "symbol": "ZW",
          "name": "Wheat futures · Commodity",
          "price": 610.25,
          "changePct": -2.203525641025641,
          "url": "https://www.cmegroup.com/search.html?q=Wheat%20futures"
        },
        {
          "symbol": "BZ",
          "name": "Brent crude futures · Commodity",
          "price": 91.7,
          "changePct": -2.144914207779244,
          "url": "https://www.cmegroup.com/search.html?q=Brent%20crude%20futures"
        },
        {
          "symbol": "ZC",
          "name": "Corn futures · Commodity",
          "price": 447,
          "changePct": -1.9199122325836533,
          "url": "https://www.cmegroup.com/search.html?q=Corn%20futures"
        },
        {
          "symbol": "CL",
          "name": "WTI crude futures · Commodity",
          "price": 87.76,
          "changePct": -1.282341401925674,
          "url": "https://www.cmegroup.com/search.html?q=WTI%20crude%20futures"
        },
        {
          "symbol": "CT",
          "name": "Cotton futures · Commodity",
          "price": 76.25,
          "changePct": -0.6773435792684387,
          "url": "https://www.cmegroup.com/search.html?q=Cotton%20futures"
        },
        {
          "symbol": "ZS",
          "name": "Soybean futures · Commodity",
          "price": 1186.5,
          "changePct": -0.6697362913352868,
          "url": "https://www.cmegroup.com/search.html?q=Soybean%20futures"
        },
        {
          "symbol": "PA",
          "name": "Palladium futures · Commodity",
          "price": 1368.5,
          "changePct": -0.6605673451806638,
          "url": "https://www.cmegroup.com/search.html?q=Palladium%20futures"
        },
        {
          "symbol": "NG",
          "name": "Natural gas futures · Commodity",
          "price": 3.273,
          "changePct": -0.3652994069147443,
          "url": "https://www.cmegroup.com/search.html?q=Natural%20gas%20futures"
        },
        {
          "symbol": "SI",
          "name": "Silver futures · Commodity",
          "price": 75.585,
          "changePct": -0.07931343212229724,
          "url": "https://www.cmegroup.com/search.html?q=Silver%20futures"
        },
        {
          "symbol": "HG",
          "name": "Copper futures · Commodity",
          "price": 6.394,
          "changePct": -0.03126811250613366,
          "url": "https://www.cmegroup.com/search.html?q=Copper%20futures"
        }
      ]
    }
  },
  "fx": [
    {
      "code": "USD",
      "pair": "SGD/USD",
      "label": "1 SGD buys USD",
      "rate": 0.78305,
      "changePct": 0,
      "url": "https://eservices.mas.gov.sg/Statistics/msb/ExchangeRates.aspx"
    },
    {
      "code": "EUR",
      "pair": "SGD/EUR",
      "label": "1 SGD buys EUR",
      "rate": 0.67249,
      "changePct": 0,
      "url": "https://eservices.mas.gov.sg/Statistics/msb/ExchangeRates.aspx"
    },
    {
      "code": "GBP",
      "pair": "SGD/GBP",
      "label": "1 SGD buys GBP",
      "rate": 0.58321,
      "changePct": 0,
      "url": "https://eservices.mas.gov.sg/Statistics/msb/ExchangeRates.aspx"
    },
    {
      "code": "AUD",
      "pair": "SGD/AUD",
      "label": "1 SGD buys AUD",
      "rate": 1.092,
      "changePct": 0,
      "url": "https://eservices.mas.gov.sg/Statistics/msb/ExchangeRates.aspx"
    },
    {
      "code": "JPY",
      "pair": "SGD/JPY",
      "label": "1 SGD buys JPY",
      "rate": 124.71,
      "changePct": 0,
      "url": "https://eservices.mas.gov.sg/Statistics/msb/ExchangeRates.aspx"
    },
    {
      "code": "CNY",
      "pair": "SGD/CNY",
      "label": "1 SGD buys CNY",
      "rate": 5.2988,
      "changePct": 0,
      "url": "https://eservices.mas.gov.sg/Statistics/msb/ExchangeRates.aspx"
    },
    {
      "code": "MYR",
      "pair": "SGD/MYR",
      "label": "1 SGD buys MYR",
      "rate": 3.1048,
      "changePct": 0,
      "url": "https://eservices.mas.gov.sg/Statistics/msb/ExchangeRates.aspx"
    },
    {
      "code": "HKD",
      "pair": "SGD/HKD",
      "label": "1 SGD buys HKD",
      "rate": 6.1357,
      "changePct": 0,
      "url": "https://eservices.mas.gov.sg/Statistics/msb/ExchangeRates.aspx"
    }
  ],
  "officialLinks": {
    "sgx": "https://www.sgx.com/securities/stock-screener",
    "us": "https://www.nasdaq.com/market-activity/stocks/screener",
    "etfs": "https://www.sgx.com/securities/etf",
    "cme": "https://www.cmegroup.com/markets.html",
    "masFx": "https://eservices.mas.gov.sg/Statistics/msb/ExchangeRates.aspx"
  }
}
